CHANGELOG.md
CHANGELOG.rst
LICENSE
MANIFEST.in
README.md
README.rst
requirements.txt
setup.py
datagristle/__init__.py
datagristle/_version.py
datagristle/common.py
datagristle/configulator.py
datagristle/csvhelper.py
datagristle/field_determinator.py
datagristle/field_math.py
datagristle/field_misc.py
datagristle/field_type.py
datagristle/file_deduper.py
datagristle/file_delta.py
datagristle/file_freaker.py
datagristle/file_io.py
datagristle/file_sorter.py
datagristle/file_type.py
datagristle/file_validator.py
datagristle/foobar.py
datagristle/helpdoc.py
datagristle/location_slicer_bkup.py
datagristle/metadata.py
datagristle/preferences.py
datagristle/simplesql.py
datagristle/slice_processor.py
datagristle/slice_specs.py
datagristle/test_tools.py
datagristle.egg-info/PKG-INFO
datagristle.egg-info/SOURCES.txt
datagristle.egg-info/dependency_links.txt
datagristle.egg-info/requires.txt
datagristle.egg-info/top_level.txt
docs/diagrams.graphml
docs/etl_analysis_waterfall_approach_diagram.graphml
docs/gristle_datamodel.odg
docs/gristle_diagrams.odg
docs/gristle_image.gif
docs/metadata_database.txt
docs/tutorial/slicer0.png
docs/tutorial/slicer1.png
docs/tutorial/slicer2.png
docs/tutorial/slicer3.png
docs/tutorial/slicer4.png
docs/tutorial/slicer5.png
docs/tutorial/slicer6.png
docs/tutorial/slicer7.png
docs/tutorial/slicer8.png
docs/tutorial/slicer_diagrams.odg
scripts/gristle_converter
scripts/gristle_determinator
scripts/gristle_differ
scripts/gristle_dir_merger
scripts/gristle_file_converter
scripts/gristle_freaker
scripts/gristle_md_reporter
scripts/gristle_metadata
scripts/gristle_profiler
scripts/gristle_slicer
scripts/gristle_sorter
scripts/gristle_validator
scripts/gristle_viewer