Metadata-Version: 2.1
Name: datagristle
Version: 0.2.3
Summary: A toolbox and library of ETL, data quality, and data analysis tools
Home-page: http://github.com/kenfar/DataGristle
Author: Ken Farmer
Author-email: kenfar@gmail.com
License: BSD
Keywords: data analysis quality utility etl
Platform: UNKNOWN
Classifier: Development Status :: 4 - Beta
Classifier: Environment :: Console
Classifier: Intended Audience :: Developers
Classifier: Intended Audience :: Information Technology
Classifier: Intended Audience :: Science/Research
Classifier: License :: OSI Approved :: BSD License
Classifier: Programming Language :: Python
Classifier: Operating System :: POSIX
Classifier: Topic :: Scientific/Engineering
Classifier: Topic :: Database
Classifier: Topic :: Scientific/Engineering :: Information Analysis
Classifier: Topic :: Text Processing
Classifier: Topic :: Utilities
